{
  "articleGroupIds": [
    "B2-843"
  ],
  "articleId": "00-395233",
  "articleOnlyCanonicalPath": "/produkte/loreal-magic-retouch-dunkelbraun-bis-schwarzbraun/00-395233",
  "attributes": [
    "s_marke",
    "mengehaus",
    "s_ranking"
  ],
  "authenticatedOnly": false,
  "availability": 4,
  "badges": [],
  "brand": "L'Oreal",
  "brandPath": "/marken/loreal",
  "canonicalPath": "/produkte/loreal-magic-retouch-dunkelbraun-bis-schwarzbraun/00-395233",
  "category": "Pflege",
  "description": "Mit dem Magic Retouch Ansatz-Kaschierspray werden graue Ansätze schonend in nur 3 Sekunden abgedeckt.<br>Der praktische Spray im Handtaschenformat<br><li>reicht für bis zu 25 Anwendungen</li><li>hält bis zur nächsten Haarwäsche und</li><li>ist wetter-, schweiß- und stylingfest</li><br>Der Magic Retouch Spray deckt 85% aller Haarfarben perfekt ab.",
  "eanCodes": [
    "3600523193196"
  ],
  "foodInformation": [
    {
      "allergens": [],
      "attributeGroups": [],
      "contacts": [
        {
          "channel": "Adresse",
          "detail": "Hertzstr. 175\n76187 Karlsruhe\nDeutschland",
          "type": "Anschrift"
        },
        {
          "channel": "Name",
          "detail": "L'Oréal Deutschland GmbH",
          "type": "Anschrift"
        }
      ],
      "countryOrigins": [
        "BELGIEN"
      ],
      "fromDate": "2020-03-24T00:00:00",
      "measurements": [
        {
          "type": "Bruttogewicht",
          "unit": "Gramm",
          "value": 73
        },
        {
          "type": "Nettogehalt",
          "unit": "Milliliter",
          "value": 75
        }
      ],
      "nutritions": [],
      "preperations": []
    }
  ],
  "grammage": "75 Milliliter Stück",
  "grammagePriceFactor": 1,
  "grammageUnit": "",
  "hasBrandTab": false,
  "hasDescription": true,
  "hasSpecialDeliveryWindows": false,
  "isAvailable": true,
  "isDelicatessen": false,
  "isMedical": false,
  "isSugarFree": false,
  "isSugarReduced": false,
  "isWeightArticle": false,
  "loyaltyPrice": {
    "bulkDiscountPriceTypes": [],
    "defaultPriceTypes": [],
    "final": 10.99,
    "isPlusPromotion": false,
    "isQuantityDiscount": false,
    "normal": 10.99,
    "priceAdditionalInfo": {},
    "priceTypeDefinitions": [],
    "sale": 10.99
  },
  "maximalOrderQuantity": 6,
  "minimalOrderQuantity": 0,
  "name": "L'Oreal Magic Retouch Dunkelbraun bis Schwarzbraun",
  "orderQuantityStepSize": 1,
  "paths": [
    "~/warengruppe/pflege/haarpflege-und-haarfarben/haarfarben/B2-843/produkte/loreal-magic-retouch-dunkelbraun-bis-schwarzbraun/00-395233"
  ],
  "price": {
    "bulkDiscountPriceTypes": [],
    "defaultPriceTypes": [],
    "final": 10.99,
    "isPlusPromotion": false,
    "isQuantityDiscount": false,
    "normal": 10.99,
    "priceAdditionalInfo": {},
    "priceTypeDefinitions": [],
    "sale": 10.99
  },
  "properties": [],
  "quantitySteps": [],
  "rank": 48700,
  "recommendationArticleIds": [],
  "seoDescription": "L'Oreal Magic Retouch Dunkelbraun bis Schwarzbraun online kaufen im BILLA Online Shop! ✔ große Produktauswahl ✔ gleiche Preise wie im Markt >> bestellen Sie jetzt!",
  "seoTitle": "L'Oreal Magic Retouch Dunkelbraun bis Schwarzbraun online bestell",
  "slug": "loreal-magic-retouch-dunkelbraun-bis-schwarzbraun",
  "storeAvalibility": [
    "00-3043",
    "00-6871",
    "00-7759",
    "00-3445",
    "00-7114",
    "00-3468",
    "00-4925",
    "00-8940",
    "00-4672",
    "00-7642",
    "00-9415",
    "00-4748",
    "00-5290",
    "00-8657",
    "00-5967",
    "00-6480",
    "00-7566",
    "00-6138",
    "00-3212",
    "00-823",
    "00-7676",
    "00-7866",
    "00-2295",
    "00-3062",
    "00-1016",
    "00-3023",
    "00-7204",
    "00-3005",
    "00-3841",
    "00-6281",
    "00-6496",
    "00-6197",
    "00-6559",
    "00-7733",
    "00-2222",
    "00-3027",
    "00-3688",
    "00-7975",
    "00-4421",
    "00-2190",
    "00-6928",
    "00-4619",
    "00-3401",
    "00-3996",
    "00-7860",
    "00-7232",
    "00-290",
    "00-8646",
    "00-4629",
    "00-4675",
    "00-7368",
    "00-3444",
    "00-6424",
    "00-2301",
    "00-7653",
    "00-7895",
    "00-4076",
    "00-4170",
    "00-4982",
    "00-4099",
    "00-3633",
    "00-281",
    "00-2223",
    "00-4226",
    "00-1132",
    "00-3220",
    "00-8085",
    "00-8235",
    "00-4707",
    "00-1099",
    "00-7857",
    "00-1580",
    "00-5000",
    "00-6688",
    "00-6724",
    "00-4655",
    "00-8158",
    "00-4489",
    "00-6892",
    "00-2201",
    "00-5777",
    "00-7743",
    "00-3094",
    "00-3713",
    "00-6508",
    "00-4146",
    "00-4952",
    "00-8151",
    "00-3121",
    "00-3584",
    "00-8241",
    "00-2011",
    "00-3082",
    "00-4059",
    "00-7491",
    "00-4605",
    "00-6749",
    "00-5108",
    "00-6494",
    "00-3118",
    "00-3131",
    "00-1476",
    "00-2109",
    "00-5322",
    "00-3681",
    "00-4700",
    "00-9030",
    "00-6490",
    "00-3714",
    "00-8334",
    "00-8188",
    "00-6970",
    "00-2204",
    "00-3739",
    "00-10",
    "00-4441",
    "00-1032",
    "00-4660",
    "00-2111",
    "00-7600",
    "00-1550",
    "00-239",
    "00-3253",
    "00-3560",
    "00-3538",
    "00-4090",
    "00-6916",
    "00-7139",
    "00-7758",
    "00-1108",
    "00-7229",
    "00-4283",
    "00-4945",
    "00-3583",
    "00-8070",
    "00-9894",
    "00-7920",
    "00-7062",
    "00-3050",
    "00-1701",
    "00-6001",
    "00-7544",
    "00-4001",
    "00-4126",
    "00-6900",
    "00-3420",
    "00-3415",
    "00-3617",
    "00-6051",
    "00-4783",
    "00-2208",
    "00-6533",
    "00-7393",
    "00-3025",
    "00-1041",
    "00-6811",
    "00-6979",
    "00-3294",
    "00-7328",
    "00-7336",
    "00-6810",
    "00-9209",
    "00-7245",
    "00-5414",
    "00-6843",
    "00-9753",
    "00-4107",
    "00-2313",
    "00-8395",
    "00-5552",
    "00-8173",
    "00-9357",
    "00-3512",
    "00-1088",
    "00-7302",
    "00-6022",
    "00-1198",
    "00-7783",
    "00-3296",
    "00-7810",
    "00-7547",
    "00-9290",
    "00-9688",
    "00-2098",
    "00-5871",
    "00-3384",
    "00-3871",
    "00-6684",
    "00-4003",
    "00-4840",
    "00-3940",
    "00-3740",
    "00-4838",
    "00-3920",
    "00-3252",
    "00-4270",
    "00-3711",
    "00-4350",
    "00-3979",
    "00-3379",
    "00-1070",
    "00-9324",
    "00-6975",
    "00-2312",
    "00-3709",
    "00-7084",
    "00-7716",
    "00-6569",
    "00-6179",
    "00-8426",
    "00-3824",
    "00-3042",
    "00-3102",
    "00-8140",
    "00-5405",
    "00-7963",
    "00-2045",
    "00-4424",
    "00-2170",
    "00-6306",
    "00-3580",
    "00-8076",
    "00-7120",
    "00-9498",
    "00-6805",
    "00-1524",
    "00-4813",
    "00-6255",
    "00-5391",
    "00-1425",
    "00-4249",
    "00-2306",
    "00-3780",
    "00-6760",
    "00-7075",
    "00-1017",
    "00-6745",
    "00-7535",
    "00-2220",
    "00-6489",
    "00-8031",
    "00-2100",
    "00-1900",
    "00-471",
    "00-3579",
    "00-2259",
    "00-2342",
    "00-4016",
    "00-4440",
    "00-3869",
    "00-4847",
    "00-7766",
    "00-7629",
    "00-9639",
    "00-5003",
    "00-2808",
    "00-8946",
    "00-3120",
    "00-3848",
    "00-1911",
    "00-3143",
    "00-3819",
    "00-7606",
    "00-8636",
    "00-1098",
    "00-7616",
    "00-3326",
    "00-440",
    "00-8606",
    "00-5531",
    "00-4565",
    "00-2907",
    "00-5603",
    "00-3114",
    "00-7609",
    "00-4690",
    "00-5104",
    "00-7358",
    "00-408",
    "00-3744",
    "00-1114",
    "00-2156",
    "00-99202"
  ],
  "url": "/produkte/loreal-magic-retouch-dunkelbraun-bis-schwarzbraun/00-395233",
  "vatCode": "20",
  "video": ""
}