{
  "articleGroupIds": [
    "B2-316"
  ],
  "articleId": "00-413861",
  "articleOnlyCanonicalPath": "/produkte/diezano-orange2/00-413861",
  "attributes": [
    "s_marke",
    "s_einweg",
    "mengehaus",
    "s_ranking",
    "mengenstep"
  ],
  "authenticatedOnly": false,
  "availability": 0,
  "badges": [],
  "brand": "Diezano",
  "canonicalPath": "/produkte/diezano-orange2/00-413861",
  "category": "Getränke",
  "description": "Diezano Orange mit frischem Quellwasser und natürlichen Aroma,  durch Beigabe von Orangensaft schmeckt es besonders fruchtig.",
  "eanCodes": [
    "0000090165832"
  ],
  "foodInformation": [
    {
      "allergens": [],
      "attributeGroups": [
        {
          "attributes": [
            {
              "attributeCode": "PACKAGINGMARKSLABELACCREDITATION",
              "description": "Umwelt und Verpackung ",
              "hasTranslation": "True",
              "value": "GREEN_DOT",
              "valueTranslation": "GREEN DOT - ARA (Verpackungskennzeichen)"
            }
          ],
          "description": "Labelinformationen",
          "groupCode": "LABEL"
        }
      ],
      "contacts": [
        {
          "channel": "Adresse",
          "detail": "Fohrenburgstr. 5, A-6700 Bludenz, Austria",
          "type": "Anschrift"
        },
        {
          "channel": "Name",
          "detail": "Brauerei Fohrenburg",
          "type": "Anschrift"
        }
      ],
      "countryOrigins": [],
      "fromDate": "2019-05-23T00:00:00",
      "ingredients": "Zutaten: Wasser, Zucker, 1,9 % Orangensaft aus Orangensaftkonzentrat, Kohlensäure, Säuerungsmittel Citronensäure, Stabilisatoren: Gummi arabicum, Glycerinester aus Wurzelharz; Antioxidationsmittel Ascorbinsäure, natürliches Orangenaroma, Farbstoffe: Carotin, Beta-apo-8`-Carotinal (C30)",
      "measurements": [
        {
          "type": "Bruttogewicht",
          "unit": "Kilogramm",
          "value": 1.58
        },
        {
          "type": "Nettogehalt",
          "unit": "Liter",
          "value": 1.5
        }
      ],
      "name": "Erfrischungsgetränk mit Orangengeschmack",
      "nutritions": [
        {
          "householdPortion": "",
          "nutritions": [
            {
              "dailyRequirementPercent": 5,
              "measureDefinition": "~",
              "nutritionName": "Energie",
              "nutritionalValue": 95,
              "unit": "Kilokalorie"
            },
            {
              "dailyRequirementPercent": 5,
              "measureDefinition": "~",
              "nutritionName": "Energie",
              "nutritionalValue": 398,
              "unit": "Kilojoule"
            },
            {
              "dailyRequirementPercent": 0,
              "measureDefinition": "~",
              "nutritionName": "Fett",
              "nutritionalValue": 0,
              "unit": "Gramm"
            },
            {
              "dailyRequirementPercent": 0,
              "measureDefinition": "~",
              "nutritionName": "   davon gesättigte Fettsäuren",
              "nutritionalValue": 0,
              "unit": "Gramm"
            },
            {
              "dailyRequirementPercent": 9,
              "measureDefinition": "~",
              "nutritionName": "Kohlenhydrate",
              "nutritionalValue": 23,
              "unit": "Gramm"
            },
            {
              "dailyRequirementPercent": 26,
              "measureDefinition": "~",
              "nutritionName": "   davon Zucker",
              "nutritionalValue": 23,
              "unit": "Gramm"
            },
            {
              "dailyRequirementPercent": 0,
              "measureDefinition": "~",
              "nutritionName": "Eiweiß",
              "nutritionalValue": 0,
              "unit": "Gramm"
            },
            {
              "dailyRequirementPercent": 0,
              "measureDefinition": "~",
              "nutritionName": "Salz",
              "nutritionalValue": 0,
              "unit": "Gramm"
            }
          ],
          "preperationGrade": "Unzubereitet für 1 Portion",
          "relationValue": 1,
          "unit": "Portion"
        },
        {
          "householdPortion": "",
          "nutritions": [
            {
              "measureDefinition": "~",
              "nutritionName": "Energie",
              "nutritionalValue": 38,
              "unit": "Kilokalorie"
            },
            {
              "measureDefinition": "~",
              "nutritionName": "Energie",
              "nutritionalValue": 159,
              "unit": "Kilojoule"
            },
            {
              "measureDefinition": "~",
              "nutritionName": "Fett",
              "nutritionalValue": 0,
              "unit": "Gramm"
            },
            {
              "measureDefinition": "~",
              "nutritionName": "   davon gesättigte Fettsäuren",
              "nutritionalValue": 0,
              "unit": "Gramm"
            },
            {
              "measureDefinition": "~",
              "nutritionName": "Kohlenhydrate",
              "nutritionalValue": 9.2,
              "unit": "Gramm"
            },
            {
              "measureDefinition": "~",
              "nutritionName": "   davon Zucker",
              "nutritionalValue": 9.2,
              "unit": "Gramm"
            },
            {
              "measureDefinition": "~",
              "nutritionName": "Eiweiß",
              "nutritionalValue": 0,
              "unit": "Gramm"
            },
            {
              "measureDefinition": "~",
              "nutritionName": "Salz",
              "nutritionalValue": 0,
              "unit": "Gramm"
            }
          ],
          "preperationGrade": "Unzubereitet für 100 Milliliter",
          "relationValue": 100,
          "unit": "Milliliter"
        }
      ],
      "portions": 6,
      "preperations": []
    }
  ],
  "grammage": "1.5 l Flasche (Einweg)",
  "grammageBadge": "1.5 l",
  "grammagePriceFactor": 1,
  "grammageUnit": "",
  "hasBrandTab": false,
  "hasDescription": true,
  "hasSpecialDeliveryWindows": false,
  "isAvailable": true,
  "isDelicatessen": false,
  "isMedical": false,
  "isSugarFree": false,
  "isSugarReduced": false,
  "isWeightArticle": false,
  "loyaltyPrice": {
    "bulkDiscountPriceTypes": [],
    "defaultPriceTypes": [],
    "final": 1.45,
    "isPlusPromotion": false,
    "isQuantityDiscount": false,
    "normal": 1.45,
    "priceAdditionalInfo": {},
    "priceTypeDefinitions": [],
    "sale": 1.45,
    "unit": "1 l .97"
  },
  "maximalOrderQuantity": 36,
  "minimalOrderQuantity": 0,
  "name": "Diezano Orange",
  "orderQuantityStepSize": 1,
  "paths": [
    "~/warengruppe/getraenke/alkoholfreie-getraenke/limonaden/B2-316/produkte/diezano-orange2/00-413861"
  ],
  "price": {
    "bulkDiscountPriceTypes": [],
    "defaultPriceTypes": [],
    "final": 1.45,
    "isPlusPromotion": false,
    "isQuantityDiscount": false,
    "normal": 1.45,
    "priceAdditionalInfo": {},
    "priceTypeDefinitions": [],
    "sale": 1.45,
    "unit": "1 l .97"
  },
  "properties": [],
  "quantitySteps": [
    6,
    12,
    18,
    24,
    30
  ],
  "rank": 38540,
  "recommendationArticleIds": [],
  "seoDescription": "Diezano Orange online kaufen im BILLA Online Shop! ✔ frisch geliefert ✔ große Produktauswahl ✔ gleiche Preise wie im Markt >> bestellen Sie jetzt!",
  "seoTitle": "Diezano Orange online bestellen | BILLA",
  "slug": "diezano-orange2",
  "storeAvalibility": [
    "00-8530",
    "00-8409",
    "00-8395",
    "00-8400",
    "00-99202"
  ],
  "url": "/produkte/diezano-orange2/00-413861",
  "vatCode": "20",
  "video": ""
}