{
  "articleGroupIds": [
    "B2-459"
  ],
  "articleId": "00-653677",
  "articleOnlyCanonicalPath": "/produkte/vorarlberger-milch-laendle-pudding-schokolade/00-653677",
  "attributes": [
    "s_marke",
    "s_ranking",
    "s_spezeig",
    "s_gekuehlt",
    "s_guetesie"
  ],
  "authenticatedOnly": false,
  "availability": 0,
  "badges": [],
  "brand": "Vorarlberg Milch",
  "canonicalPath": "/produkte/vorarlberger-milch-laendle-pudding-schokolade/00-653677",
  "category": "Kühlwaren",
  "description": "Cremig, zart und fein – so schmeckt der Ländle Schoko-Pudding aus frischer Milch und Süßrahm der heimischen Vorarlberg Milch Molkerei.<li>Pudding mit Schokoladengeschmack",
  "eanCodes": [
    "9021700188004"
  ],
  "foodInformation": [
    {
      "allergens": [
        {
          "allergenName": "Milch und Milcherzeugnisse",
          "grade": "Enthält - Ist im Produkt enthalten"
        }
      ],
      "attributeGroups": [
        {
          "attributes": [
            {
              "attributeCode": "PACKAGINGMARKSLABELACCREDITATION",
              "description": "Umwelt und Verpackung ",
              "hasTranslation": "True",
              "value": "AMA_SEAL_OF_APPROVAL",
              "valueTranslation": "AMA-Gütesiegel (Qualitätskontrolle, Österreich)"
            },
            {
              "attributeCode": "PACKAGINGMARKSLABELACCREDITATION",
              "description": "Umwelt und Verpackung ",
              "hasTranslation": "True",
              "value": "LAENDLE_QUALITAET",
              "valueTranslation": "LAENDLE-Qualitätssiegel - (Vorarlberger Produkte, definierte Qualitätsstandards)"
            },
            {
              "attributeCode": "PACKAGINGMARKSLABELACCREDITATION",
              "description": "Umwelt und Verpackung ",
              "hasTranslation": "True",
              "value": "IGT",
              "valueTranslation": "Identitätskennzeichen  und Genusstauglichkeitskennzeichen"
            },
            {
              "attributeCode": "PACKAGINGMARKSLABELACCREDITATION",
              "description": "Umwelt und Verpackung ",
              "hasTranslation": "True",
              "value": "GREEN_DOT",
              "valueTranslation": "GREEN DOT - ARA (Verpackungskennzeichen)"
            }
          ],
          "description": "Labelinformationen",
          "groupCode": "LABEL"
        }
      ],
      "contacts": [
        {
          "channel": "Adresse",
          "detail": "Nofler Straße 62, A-6800 Feldkirch",
          "type": "Anschrift"
        },
        {
          "channel": "Name",
          "detail": "Vorarlberg Milch eGen",
          "type": "Anschrift"
        }
      ],
      "countryOrigins": [
        "ÖSTERREICH"
      ],
      "fromDate": "2022-03-08T00:00:00",
      "ingredients": "Zutaten: VOLLMILCH, 17% SÜßRAHM (36% Fett), Zucker, modifizierte Maisstärke, 1,9% Schokoladepulver (Kakao, Zucker), Verdickungsmittel: Carrageen, Xanthan, Aroma",
      "measurements": [
        {
          "type": "Bruttogewicht",
          "unit": "Gramm",
          "value": 159
        },
        {
          "type": "Nettogehalt",
          "unit": "Gramm",
          "value": 150
        }
      ],
      "name": "Pudding Schokolade",
      "nutritions": [
        {
          "householdPortion": "",
          "nutritions": [
            {
              "measureDefinition": "~",
              "nutritionName": "Energie",
              "nutritionalValue": 161,
              "unit": "Kilokalorie"
            },
            {
              "measureDefinition": "~",
              "nutritionName": "Energie",
              "nutritionalValue": 677,
              "unit": "Kilojoule"
            },
            {
              "measureDefinition": "~",
              "nutritionName": "Fett",
              "nutritionalValue": 8.7,
              "unit": "Gramm"
            },
            {
              "measureDefinition": "~",
              "nutritionName": "   davon gesättigte Fettsäuren",
              "nutritionalValue": 5.7,
              "unit": "Gramm"
            },
            {
              "measureDefinition": "~",
              "nutritionName": "Kohlenhydrate",
              "nutritionalValue": 17.9,
              "unit": "Gramm"
            },
            {
              "measureDefinition": "~",
              "nutritionName": "   davon Zucker",
              "nutritionalValue": 17.7,
              "unit": "Gramm"
            },
            {
              "measureDefinition": "~",
              "nutritionName": "Eiweiß",
              "nutritionalValue": 2.9,
              "unit": "Gramm"
            },
            {
              "measureDefinition": "~",
              "nutritionName": "Salz",
              "nutritionalValue": 0.13,
              "unit": "Gramm"
            }
          ],
          "preperationGrade": "Unzubereitet für 100 Gramm",
          "relationValue": 100,
          "unit": "Gramm"
        }
      ],
      "preperations": [],
      "storageHint": "gekühlt mindestens haltbar bis: siehe Deckel"
    }
  ],
  "grammage": "150 Gramm Packung",
  "grammagePriceFactor": 1,
  "grammageUnit": "",
  "hasBrandTab": false,
  "hasDescription": true,
  "hasSpecialDeliveryWindows": false,
  "isAvailable": true,
  "isDelicatessen": false,
  "isMedical": false,
  "isSugarFree": false,
  "isSugarReduced": false,
  "isWeightArticle": false,
  "loyaltyPrice": {
    "bulkDiscountPriceTypes": [],
    "defaultPriceTypes": [],
    "final": 0.79,
    "isPlusPromotion": false,
    "isQuantityDiscount": false,
    "normal": 0.79,
    "priceAdditionalInfo": {},
    "priceTypeDefinitions": [],
    "sale": 0.79,
    "unit": "1 kg 5.27"
  },
  "maximalOrderQuantity": 999,
  "minimalOrderQuantity": 0,
  "name": "Vorarlberger Milch Ländle Pudding Schokolade",
  "orderQuantityStepSize": 1,
  "paths": [
    "~/warengruppe/kuehlwaren/milchprodukte/pudding-und-desserts/B2-459/produkte/vorarlberger-milch-laendle-pudding-schokolade/00-653677"
  ],
  "price": {
    "bulkDiscountPriceTypes": [],
    "defaultPriceTypes": [],
    "final": 0.79,
    "isPlusPromotion": false,
    "isQuantityDiscount": false,
    "normal": 0.79,
    "priceAdditionalInfo": {},
    "priceTypeDefinitions": [],
    "sale": 0.79,
    "unit": "1 kg 5.27"
  },
  "properties": [
    "Chilled"
  ],
  "quantitySteps": [],
  "rank": 63120,
  "recommendationArticleIds": [],
  "seoDescription": "Vorarlberger Milch Ländle Pudding Schokolade online kaufen im BILLA Online Shop! ✔ große Produktauswahl ✔ gleiche Preise wie im Markt >> bestellen Sie jetzt!",
  "seoTitle": "Vorarlberger Milch Ländle Pudding Schokolade online bestellen",
  "slug": "vorarlberger-milch-laendle-pudding-schokolade",
  "storeAvalibility": [
    "00-8409",
    "00-99202",
    "00-8530",
    "00-8400",
    "00-8395"
  ],
  "url": "/produkte/vorarlberger-milch-laendle-pudding-schokolade/00-653677",
  "vatCode": "10",
  "video": ""
}