{
  "articleGroupIds": [
    "B2-319"
  ],
  "articleId": "00-782679",
  "articleOnlyCanonicalPath": "/produkte/monin-veilchen-sirup/00-782679",
  "attributes": [
    "s_marke",
    "s_einweg",
    "mengehaus",
    "s_ranking",
    "mengenstep"
  ],
  "authenticatedOnly": false,
  "availability": 4,
  "badges": [],
  "brand": "Monin",
  "canonicalPath": "/produkte/monin-veilchen-sirup/00-782679",
  "category": "Getränke",
  "description": "Der Veilchensirup von Monin hat ein intensiv-florales Aroma. Er eignet sich zum Mischen von Cocktails und Longdrinks oder auch als Zusatz zum Tee.<li>zum Mischen, Mixen und Kolorieren",
  "eanCodes": [
    "3052910019556"
  ],
  "foodInformation": [
    {
      "allergens": [],
      "attributeGroups": [
        {
          "attributes": [
            {
              "attributeCode": "PACKAGINGMARKSLABELACCREDITATION",
              "description": "Umwelt und Verpackung ",
              "hasTranslation": "True",
              "value": "GREEN_DOT",
              "valueTranslation": "GREEN DOT - ARA (Verpackungskennzeichen)"
            }
          ],
          "description": "Labelinformationen",
          "groupCode": "LABEL"
        }
      ],
      "contacts": [
        {
          "channel": "Adresse",
          "detail": "18000 BOURGES - FRANCE",
          "type": "Anschrift"
        },
        {
          "channel": "Name",
          "detail": "Monin",
          "type": "Anschrift"
        },
        {
          "channel": "Webseite",
          "detail": "www.monin.com",
          "type": "Kontaktinformation"
        }
      ],
      "countryOrigins": [
        "FRANKREICH"
      ],
      "fromDate": "2019-05-24T00:00:00",
      "ingredients": "Zutaten: Zucker, Wasser, Säuerungsmittel: Citronensäure, Veilchenaroma, Farbstoffe: E163, E133.",
      "measurements": [
        {
          "type": "Bruttogewicht",
          "unit": "Gramm",
          "value": 500
        },
        {
          "type": "Nettogehalt",
          "unit": "Liter",
          "value": 0.25
        }
      ],
      "name": "Veilchen Sirup",
      "nutritions": [
        {
          "householdPortion": "",
          "nutritions": [
            {
              "measureDefinition": "~",
              "nutritionName": "Energie",
              "nutritionalValue": 306,
              "unit": "Kilokalorie"
            },
            {
              "measureDefinition": "~",
              "nutritionName": "Energie",
              "nutritionalValue": 1279,
              "unit": "Kilojoule"
            },
            {
              "measureDefinition": "~",
              "nutritionName": "Fett",
              "nutritionalValue": 0,
              "unit": "Gramm"
            },
            {
              "measureDefinition": "~",
              "nutritionName": "   davon gesättigte Fettsäuren",
              "nutritionalValue": 0,
              "unit": "Gramm"
            },
            {
              "measureDefinition": "~",
              "nutritionName": "Kohlenhydrate",
              "nutritionalValue": 75,
              "unit": "Gramm"
            },
            {
              "measureDefinition": "~",
              "nutritionName": "   davon Zucker",
              "nutritionalValue": 75,
              "unit": "Gramm"
            },
            {
              "measureDefinition": "~",
              "nutritionName": "Eiweiß",
              "nutritionalValue": 0,
              "unit": "Gramm"
            },
            {
              "measureDefinition": "~",
              "nutritionName": "Salz",
              "nutritionalValue": 0.01,
              "unit": "Gramm"
            }
          ],
          "preperationGrade": "Unzubereitet für 100 Milliliter",
          "relationValue": 100,
          "unit": "Milliliter"
        }
      ],
      "preperations": []
    }
  ],
  "grammage": "0.25 l Flasche (Einweg)",
  "grammageBadge": "0.25 l",
  "grammagePriceFactor": 1,
  "grammageUnit": "",
  "hasBrandTab": false,
  "hasDescription": true,
  "hasSpecialDeliveryWindows": false,
  "isAvailable": true,
  "isDelicatessen": false,
  "isMedical": false,
  "isSugarFree": false,
  "isSugarReduced": false,
  "isWeightArticle": false,
  "loyaltyPrice": {
    "bulkDiscountPriceTypes": [],
    "defaultPriceTypes": [],
    "final": 4.29,
    "isPlusPromotion": false,
    "isQuantityDiscount": false,
    "normal": 4.29,
    "priceAdditionalInfo": {},
    "priceTypeDefinitions": [],
    "sale": 4.29,
    "unit": "1 l 17.16"
  },
  "maximalOrderQuantity": 36,
  "minimalOrderQuantity": 0,
  "name": "Monin Veilchen Sirup",
  "orderQuantityStepSize": 1,
  "paths": [
    "~/warengruppe/getraenke/alkoholfreie-getraenke/sirupe/B2-319/produkte/monin-veilchen-sirup/00-782679"
  ],
  "price": {
    "bulkDiscountPriceTypes": [],
    "defaultPriceTypes": [],
    "final": 4.29,
    "isPlusPromotion": false,
    "isQuantityDiscount": false,
    "normal": 4.29,
    "priceAdditionalInfo": {},
    "priceTypeDefinitions": [],
    "sale": 4.29,
    "unit": "1 l 17.16"
  },
  "properties": [],
  "quantitySteps": [
    6,
    12,
    18,
    24,
    30
  ],
  "rank": 54130,
  "recommendationArticleIds": [
    "00-405686"
  ],
  "seoDescription": "Monin Veilchen Sirup online kaufen im BILLA Online Shop! ✔ frisch geliefert ✔ große Produktauswahl ✔ gleiche Preise wie im Markt >> bestellen Sie jetzt!",
  "seoTitle": "Monin Veilchen Sirup online bestellen | BILLA",
  "slug": "monin-veilchen-sirup",
  "storeAvalibility": [
    "00-6588",
    "00-4107",
    "00-10",
    "00-3512",
    "00-3114",
    "00-7860",
    "00-7606",
    "00-9290",
    "00-7114",
    "00-2111",
    "00-5306",
    "00-7539",
    "00-1132",
    "00-6928",
    "00-3118",
    "00-3445",
    "00-3780",
    "00-1032",
    "00-2342",
    "00-3709",
    "00-3856",
    "00-1457",
    "00-3431",
    "00-3143",
    "00-4675",
    "00-3384",
    "00-6884",
    "00-7393",
    "00-3150",
    "00-1108",
    "00-2109",
    "00-4779",
    "00-4690",
    "00-3617",
    "00-1913",
    "00-4783",
    "00-7857",
    "00-99202",
    "00-4421",
    "00-3076",
    "00-3506",
    "00-4551",
    "00-3023",
    "00-6740",
    "00-7358",
    "00-1041",
    "00-3681",
    "00-5199",
    "00-8012",
    "00-8946",
    "00-3234",
    "00-4126",
    "00-4249",
    "00-4655",
    "00-249",
    "00-3551",
    "00-4982",
    "00-174",
    "00-6533",
    "00-4605",
    "00-3857",
    "00-3700",
    "00-8213",
    "00-1128",
    "00-7653",
    "00-4932",
    "00-7084",
    "00-4524"
  ],
  "url": "/produkte/monin-veilchen-sirup/00-782679",
  "vatCode": "10",
  "video": ""
}