{
  "articleGroupIds": [
    "B2-344"
  ],
  "articleId": "00-878008",
  "articleOnlyCanonicalPath": "/produkte/kopparberg-pear-cider/00-878008",
  "attributes": [
    "s_marke",
    "mengehaus",
    "s_ranking",
    "mengenstep"
  ],
  "authenticatedOnly": false,
  "availability": 4,
  "badges": [],
  "brand": "Kopparberg",
  "canonicalPath": "/produkte/kopparberg-pear-cider/00-878008",
  "category": "Getränke",
  "description": "Der Premium Pear Cider von Kopparberg ist ein fruchtig-frischer Genuss mit 4,5 % Alkohol. Er passt hervorragend zu leichten Speisen und Salaten.<li>prickelnd frisch dank Kohlensäure<li>mit Birnensaft und fermentierten Birnen hergestellt<li>schmeckt gekühlt am besten",
  "eanCodes": [
    "7393714130006"
  ],
  "foodInformation": [
    {
      "alcoholicPercentage": 4.5,
      "allergens": [
        {
          "allergenName": "Schwefeldioxid und Sulphite",
          "grade": "Enthält - Ist im Produkt enthalten"
        }
      ],
      "attributeGroups": [],
      "contacts": [
        {
          "channel": "Adresse",
          "detail": "714 82 Kopparberg, Sweden",
          "type": "Anschrift"
        },
        {
          "channel": "Name",
          "detail": "Kopparbergs Brewery",
          "type": "Anschrift"
        }
      ],
      "countryOrigins": [
        "SCHWEDEN"
      ],
      "fromDate": "2016-07-21T00:00:00",
      "ingredients": "Zutaten: Mit Kohlensäure versetztes Wasser, fermentierte Birnen, Birnensaft, Zucker, Aromen, Säure: Zitronensäure E330, Konservierungsstoff E202, Antioxidationsmittel (E224/Sulfit).",
      "measurements": [
        {
          "type": "Bruttogewicht",
          "unit": "Gramm",
          "value": 529
        },
        {
          "type": "Nettogehalt",
          "unit": "Milliliter",
          "value": 500
        }
      ],
      "name": "Premium Cider",
      "nutritions": [],
      "preperations": []
    }
  ],
  "grammage": "0.5 l Dose",
  "grammageBadge": "0.5 l",
  "grammagePriceFactor": 1,
  "grammageUnit": "",
  "hasBrandTab": false,
  "hasDescription": true,
  "hasSpecialDeliveryWindows": false,
  "isAvailable": true,
  "isDelicatessen": false,
  "isMedical": false,
  "isSugarFree": false,
  "isSugarReduced": false,
  "isWeightArticle": false,
  "loyaltyPrice": {
    "bulkDiscountPriceTypes": [],
    "defaultPriceTypes": [
      "AKTION"
    ],
    "final": 1.49,
    "isPlusPromotion": false,
    "isQuantityDiscount": false,
    "normal": 1.99,
    "priceAdditionalInfo": {},
    "priceTypeDefinitions": [
      {
        "name": "AKTION"
      }
    ],
    "sale": 1.49,
    "unit": "1 l 3.98"
  },
  "maximalOrderQuantity": 36,
  "minimalOrderQuantity": 0,
  "name": "Kopparberg Pear Cider",
  "orderQuantityStepSize": 1,
  "paths": [
    "~/warengruppe/getraenke/sekt-und-champagner2/cider/B2-344/produkte/kopparberg-pear-cider/00-878008"
  ],
  "price": {
    "bulkDiscountPriceTypes": [],
    "defaultPriceTypes": [
      "AKTION"
    ],
    "final": 1.49,
    "isPlusPromotion": false,
    "isQuantityDiscount": false,
    "normal": 1.99,
    "priceAdditionalInfo": {},
    "priceTypeDefinitions": [
      {
        "name": "AKTION"
      }
    ],
    "sale": 1.49,
    "unit": "1 l 3.98"
  },
  "properties": [],
  "quantitySteps": [
    6,
    12,
    18,
    24,
    30
  ],
  "rank": 110320,
  "recommendationArticleIds": [
    "00-576151"
  ],
  "seoDescription": "Kopparberg Pear Cider online kaufen im BILLA Online Shop! ✔ frisch geliefert ✔ große Produktauswahl ✔ gleiche Preise wie im Markt >> bestellen Sie jetzt!",
  "seoTitle": "Kopparberg Pear Cider online bestellen | BILLA",
  "slug": "kopparberg-pear-cider",
  "storeAvalibility": [
    "00-3044",
    "00-119",
    "00-3780",
    "00-176",
    "00-99202",
    "00-2190",
    "00-2342",
    "00-6676",
    "00-771",
    "00-3042",
    "00-388",
    "00-10",
    "00-174"
  ],
  "url": "/produkte/kopparberg-pear-cider/00-878008",
  "vatCode": "20",
  "video": ""
}